mafia_rl_discord_bot/__init__.py
mafia_rl_discord_bot/discord_bot.py
mafia_rl_discord_bot/game.py
mafia_rl_discord_bot/voting.py
mafia_rl_discord_bot/config/points.json
mafia_rl_discord_bot-0.0.9.dist-info/LICENSE
mafia_rl_discord_bot-0.0.9.dist-info/METADATA
mafia_rl_discord_bot-0.0.9.dist-info/WHEEL
mafia_rl_discord_bot-0.0.9.dist-info/entry_points.txt
mafia_rl_discord_bot-0.0.9.dist-info/top_level.txt
mafia_rl_discord_bot-0.0.9.dist-info/RECORD
