Metadata-Version: 2.1
Name: mafia-rl-discord-bot
Version: 0.0.9
Summary: A discord bot to help you facilitate Mafia games on Rocket League
Home-page: https://github.com/gapuchi/mafiaBot
Author: Arjun Adhia
Author-email: arjun.adhia@gmail.com
License: UNKNOWN
Platform: UNKNOWN
Requires-Python: >=3.7
License-File: LICENSE
Requires-Dist: discord.py
Requires-Dist: appdirs
